PyRvcTest/__init__.py
PyRvcTest/tool_test.py
PyRvcTest-0.0.1.dist-info/METADATA
PyRvcTest-0.0.1.dist-info/WHEEL
PyRvcTest-0.0.1.dist-info/top_level.txt
PyRvcTest-0.0.1.dist-info/RECORD
