Metadata-Version: 2.1
Name: PyRvcTest
Version: 0.0.1
Summary: Python常用代码小工具集锦
Home-page: 
Author: 王志强
Author-email: 663856650@qq.com
License: GPLv3
Classifier: Programming Language :: Python :: 3
Classifier: License :: OSI Approved :: GNU General Public License v3 (GPLv3)
Classifier: Operating System :: OS Independent
Requires-Python: >=3.9
